fileorganizer/__init__.py
fileorganizer/cli.py
fileorganizer/organizer.py
fileorganizer_farhan-0.1.1.dist-info/licenses/LICENSE
tests/__init__.py
tests/test_cli.py
tests/test_organizer.py
fileorganizer_farhan-0.1.1.dist-info/METADATA
fileorganizer_farhan-0.1.1.dist-info/WHEEL
fileorganizer_farhan-0.1.1.dist-info/entry_points.txt
fileorganizer_farhan-0.1.1.dist-info/top_level.txt
fileorganizer_farhan-0.1.1.dist-info/RECORD
