Metadata-Version: 2.4
Name: fileorganizer-farhan
Version: 0.1.1
Summary: A tool to organize messy files into categorized folders
Home-page: https://github.com/Farhanahmad-kust/fileorganizer
Author: Farhan Ahmad
Author-email: Farhan Ahmad <farhanbangash091@gmail.com>
License-Expression: MIT
Project-URL: Homepage, https://github.com/Farhanahmad-kust/fileorganizer
Project-URL: Bug Tracker, https://github.com/Farhanahmad-kust/fileorganizer/issues
Keywords: file organization,cleanup,automation
Classifier: Programming Language :: Python :: 3
Classifier: Programming Language :: Python :: 3.9
Classifier: Programming Language :: Python :: 3.10
Classifier: Programming Language :: Python :: 3.11
Classifier: Operating System :: OS Independent
Classifier: Development Status :: 4 - Beta
Classifier: Intended Audience :: End Users/Desktop
Classifier: Topic :: Utilities
Requires-Python: >=3.9
License-File: LICENSE
Dynamic: author
Dynamic: home-page
Dynamic: license-file
Dynamic: requires-python
